streamlit_push_notifications/__init__.py
streamlit_push_notifications/streamlit_notifications.py
streamlit_push_notifications-0.1.dist-info/METADATA
streamlit_push_notifications-0.1.dist-info/WHEEL
streamlit_push_notifications-0.1.dist-info/top_level.txt
streamlit_push_notifications-0.1.dist-info/RECORD
