Metadata-Version: 2.1
Name: streamlit_push_notifications
Version: 0.1
Summary: A Streamlit library for sending browser notifications and alerts
Home-page: https://github.com/yunisguliyev/streamlit-push-notifications.git
Author: Wambugu Kinyua
Author-email: kenliz1738@gmail.com
Classifier: Programming Language :: Python :: 3
Classifier: License :: OSI Approved :: MIT License
Classifier: Operating System :: OS Independent
Requires-Python: >=3.8
Requires-Dist: streamlit>=1.0.0
